Workbook

Sheet Main Work
A1: Transaction_ID | B1: Date | C1: Department | D1: Category | E1: Type | F1: Actual_Amount_GHS | G1: Budget_Amount_GHS | H1: Payment_Method | I1: Location | J1: Month | K1: Year | L1: Variance | M1: Total Transactions | N1: Total Revenue | O1: Total Expenses | P1: Profit
A2: TXN-0001 | B2: 46091 | C2: Sales | D2: Office Supplies | E2: Expense | F2: 5486 | G2: 5679 | H2: Bank | I2: Kumasi | J2: Mar | K2: 2026 | L2: =F2-G2 -> -193 | M2: =COUNTA(A2:A181) -> 180 | N2: =SUMIF(E2:E181,"Revenue",F2:F181) -> 318721 | O2: =SUMIF(E2:E181,"Expense",F2:F181) -> 456287 | P2: =N2-O2 -> -137566
A3: TXN-0002 | B3: 46118 | C3: Administration | D3: Sales | E3: Revenue | F3: 17011 | G3: 15857 | H3: Mobile Money | I3: Takoradi | J3: Apr | K3: 2026 | L3: =F3-G3 -> 1154 | M3: =COUNTA(A3:A182) -> 179 | N3: =SUMIF(E3:E182,"Revenue",F3:F182) -> 318721 | O3: =SUMIF(E3:E182,"Expense",F3:F182) -> 450801 | P3: =N3-O3 -> -132080
A4: TXN-0003 | B4: 46165 | C4: Operations | D4: Utilities | E4: Expense | F4: 113 | G4: 122 | H4: Cash | I4: Kumasi | J4: May | K4: 2026 | L4: =F4-G4 -> -9 | M4: =COUNTA(A4:A183) -> 178 | N4: =SUMIF(E4:E183,"Revenue",F4:F183) -> 301710 | O4: =SUMIF(E4:E183,"Expense",F4:F183) -> 450801 | P4: =N4-O4 -> -149091
A5: TXN-0004 | B5: 46109 | C5: Operations | D5: Rent | E5: Expense | F5: 1822 | G5: 1586 | H5: Bank | I5: Takoradi | J5: Mar | K5: 2026 | L5: =F5-G5 -> 236 | M5: =COUNTA(A5:A184) -> 177 | N5: =SUMIF(E5:E184,"Revenue",F5:F184) -> 301710 | O5: =SUMIF(E5:E184,"Expense",F5:F184) -> 450688 | P5: =N5-O5 -> -148978
A6: TXN-0005 | B6: 46197 | C6: Finance | D6: Marketing | E6: Expense | F6: 3414 | G6: 3855 | H6: Bank | I6: Accra | J6: Jun | K6: 2026 | L6: =F6-G6 -> -441 | M6: =COUNTA(A6:A185) -> 176 | N6: =SUMIF(E6:E185,"Revenue",F6:F185) -> 301710 | O6: =SUMIF(E6:E185,"Expense",F6:F185) -> 448866 | P6: =N6-O6 -> -147156
A7: TXN-0006 | B7: 46046 | C7: Finance | D7: Utilities | E7: Expense | F7: 3571 | G7: 4218 | H7: Mobile Money | I7: Kumasi | J7: Jan | K7: 2026 | L7: =F7-G7 -> -647 | M7: =COUNTA(A7:A186) -> 175 | N7: =SUMIF(E7:E186,"Revenue",F7:F186) -> 301710 | O7: =SUMIF(E7:E186,"Expense",F7:F186) -> 445452 | P7: =N7-O7 -> -143742
A8: TXN-0007 | B8: 46161 | C8: Operations | D8: Rent | E8: Expense | F8: 2660 | G8: 3082 | H8: Mobile Money | I8: Accra | J8: May | K8: 2026 | L8: =F8-G8 -> -422 | M8: =COUNTA(A8:A187) -> 174 | N8: =SUMIF(E8:E187,"Revenue",F8:F187) -> 301710 | O8: =SUMIF(E8:E187,"Expense",F8:F187) -> 441881 | P8: =N8-O8 -> -140171
A9: TXN-0008 | B9: 46152 | C9: Administration | D9: Rent | E9: Expense | F9: 784 | G9: 776 | H9: Mobile Money | I9: Takoradi | J9: May | K9: 2026 | L9: =F9-G9 -> 8 | M9: =COUNTA(A9:A188) -> 173 | N9: =SUMIF(E9:E188,"Revenue",F9:F188) -> 301710 | O9: =SUMIF(E9:E188,"Expense",F9:F188) -> 439221 | P9: =N9-O9 -> -137511
A10: TXN-0009 | B10: 46145 | C10: Finance | D10: Office Supplies | E10: Expense | F10: 5091 | G10: 5012 | H10: Mobile Money | I10: Takoradi | J10: May | K10: 2026 | L10: =F10-G10 -> 79 | M10: =COUNTA(A10:A189) -> 172 | N10: =SUMIF(E10:E189,"Revenue",F10:F189) -> 301710 | O10: =SUMIF(E10:E189,"Expense",F10:F189) -> 438437 | P10: =N10-O10 -> -136727
A11: TXN-0010 | B11: 46072 | C11: Sales | D11: Consulting | E11: Revenue | F11: 9770 | G11: 9348 | H11: Mobile Money | I11: Kumasi | J11: Feb | K11: 2026 | L11: =F11-G11 -> 422 | M11: =COUNTA(A11:A190) -> 171 | N11: =SUMIF(E11:E190,"Revenue",F11:F190) -> 301710 | O11: =SUMIF(E11:E190,"Expense",F11:F190) -> 433346 | P11: =N11-O11 -> -131636
A12: TXN-0011 | B12: 46052 | C12: Sales | D12: Transport | E12: Expense | F12: 2167 | G12: 2020 | H12: Cash | I12: Takoradi | J12: Jan | K12: 2026 | L12: =F12-G12 -> 147 | M12: =COUNTA(A12:A191) -> 170 | N12: =SUMIF(E12:E191,"Revenue",F12:F191) -> 291940 | O12: =SUMIF(E12:E191,"Expense",F12:F191) -> 433346 | P12: =N12-O12 -> -141406
A13: TXN-0012 | B13: 46030 | C13: Administration | D13: Rent | E13: Expense | F13: 3220 | G13: 3664 | H13: Bank | I13: Takoradi | J13: Jan | K13: 2026 | L13: =F13-G13 -> -444 | M13: =COUNTA(A13:A192) -> 169 | N13: =SUMIF(E13:E192,"Revenue",F13:F192) -> 291940 | O13: =SUMIF(E13:E192,"Expense",F13:F192) -> 431179 | P13: =N13-O13 -> -139239
... A181: TXN-0180 | B181: 46113 | C181: Finance | D181: Office Supplies | E181: Expense | F181: 5112 | G181: 5599 | H181: Mobile Money | I181: Takoradi | J181: Apr | K181: 2026 | L181: =F181-G181 -> -487 | M181: =COUNTA(A181:A360) -> 1 | N181: =SUMIF(E181:E360,"Revenue",F181:F360) -> 0 | O181: =SUMIF(E181:E360,"Expense",F181:F360) -> 5112 | P181: =N181-O181 -> -5112

Sheet Highest Expense Category
A1: Type | B1: Expense
A3: Category | B3: Sum of Actual_Amount_GHS
A4: Office Supplies | B4: 105273
A5: Software | B5: 94089
A6: Marketing | B6: 82806
A7: Rent | B7: 65473
A8: Transport | B8: 59773
A9: Utilities | B9: 48873
A10: Grand Total | B10: 456287

Sheet Department with Expenses
A1: Type | B1: Expense
A3: Department | B3: Sum of Actual_Amount_GHS
A4: Sales | B4: 134953
A5: Finance | B5: 126197
A6: Operations | B6: 98095
A7: Administration | B7: 97042
A8: Grand Total | B8: 456287

Sheet Summary
A2: Total Transactions | B2: =COUNTA('Main Work'!A2:A181) -> 180
A3: Total Revenue | B3: =SUMIF('Main Work'!E2:E181,"Revenue",'Main Work'!F2:F181) -> 318721
A4: Total Expenses | B4: =SUMIF('Main Work'!E2:E181,"Expense",'Main Work'!F2:F181) -> 456287
A5: Profit(Revenue - Expenses) | B5: =B3-B4 -> -137566
A6: Highest Expense Category | B6: ='Highest Expense Category'!A4 -> Office Supplies
A7: Highest Expense Caategory Amount | B7: ='Highest Expense Category'!B4 -> 105273
A8: Department with Highest Expenses | B8: ='Department with Expenses'!A4 -> Sales
A9: Department with Highest Expense Amount | B9: ='Department with Expenses'!B4 -> 134953

Sheet Financial Summary
A1: Financial Summary
A2: Total Revenue | B2: =SUMIFS('Main Work'!F2:F181,'Main Work'!E2:E181,"Revenue") -> 318721
A3: Total Expenses | B3: =SUMIFS('Main Work'!F2:F181,'Main Work'!E2:E181,"Expense") -> 456287
A4: Profit | B4: =B2-B3 -> -137566
A5: Profit Margin | B5: =B4/B2 -> -0.43161888

Sheet Monthly Analysis
A1: Month | B1: Revenue | C1: Expenses | D1: Profit
A2: Jan | B2: =SUMIFS('Main Work'!F$2:F$181,'Main Work'!E$2:E$181,"Revenue",'Main Work'!J$2:J$181,A2) -> 35345 | C2: =SUMIFS('Main Work'!F$2:F$181,'Main Work'!E$2:E$181,"Expense",'Main Work'!J$2:J$181,A2) -> 63670 | D2: =B2-C2 -> -28325
A3: Feb | B3: =SUMIFS('Main Work'!F$2:F$181,'Main Work'!E$2:E$181,"Revenue",'Main Work'!J$2:J$181,A3) -> 66064 | C3: =SUMIFS('Main Work'!F$2:F$181,'Main Work'!E$2:E$181,"Expense",'Main Work'!J$2:J$181,A3) -> 87107 | D3: =B3-C3 -> -21043
A4: Mar | B4: =SUMIFS('Main Work'!F$2:F$181,'Main Work'!E$2:E$181,"Revenue",'Main Work'!J$2:J$181,A4) -> 50426 | C4: =SUMIFS('Main Work'!F$2:F$181,'Main Work'!E$2:E$181,"Expense",'Main Work'!J$2:J$181,A4) -> 67673 | D4: =B4-C4 -> -17247
A5: Apr | B5: =SUMIFS('Main Work'!F$2:F$181,'Main Work'!E$2:E$181,"Revenue",'Main Work'!J$2:J$181,A5) -> 98466 | C5: =SUMIFS('Main Work'!F$2:F$181,'Main Work'!E$2:E$181,"Expense",'Main Work'!J$2:J$181,A5) -> 82335 | D5: =B5-C5 -> 16131
A6: May | B6: =SUMIFS('Main Work'!F$2:F$181,'Main Work'!E$2:E$181,"Revenue",'Main Work'!J$2:J$181,A6) -> 38665 | C6: =SUMIFS('Main Work'!F$2:F$181,'Main Work'!E$2:E$181,"Expense",'Main Work'!J$2:J$181,A6) -> 75276 | D6: =B6-C6 -> -36611
A7: Jun | B7: =SUMIFS('Main Work'!F$2:F$181,'Main Work'!E$2:E$181,"Revenue",'Main Work'!J$2:J$181,A7) -> 29755 | C7: =SUMIFS('Main Work'!F$2:F$181,'Main Work'!E$2:E$181,"Expense",'Main Work'!J$2:J$181,A7) -> 80226 | D7: =B7-C7 -> -50471
A8: Jul | B8: =SUMIFS('Main Work'!F$2:F$181,'Main Work'!E$2:E$181,"Revenue",'Main Work'!J$2:J$181,A8) -> 0 | C8: =SUMIFS('Main Work'!F$2:F$181,'Main Work'!E$2:E$181,"Expense",'Main Work'!J$2:J$181,A8) -> 0 | D8: =B8-C8 -> 0
A9: Aug | B9: =SUMIFS('Main Work'!F$2:F$181,'Main Work'!E$2:E$181,"Revenue",'Main Work'!J$2:J$181,A9) -> 0 | C9: =SUMIFS('Main Work'!F$2:F$181,'Main Work'!E$2:E$181,"Expense",'Main Work'!J$2:J$181,A9) -> 0 | D9: =B9-C9 -> 0
A10: Sep | B10: =SUMIFS('Main Work'!F$2:F$181,'Main Work'!E$2:E$181,"Revenue",'Main Work'!J$2:J$181,A10) -> 0 | C10: =SUMIFS('Main Work'!F$2:F$181,'Main Work'!E$2:E$181,"Expense",'Main Work'!J$2:J$181,A10) -> 0 | D10: =B10-C10 -> 0
A11: Oct | B11: =SUMIFS('Main Work'!F$2:F$181,'Main Work'!E$2:E$181,"Revenue",'Main Work'!J$2:J$181,A11) -> 0 | C11: =SUMIFS('Main Work'!F$2:F$181,'Main Work'!E$2:E$181,"Expense",'Main Work'!J$2:J$181,A11) -> 0 | D11: =B11-C11 -> 0
A12: Nov | B12: =SUMIFS('Main Work'!F$2:F$181,'Main Work'!E$2:E$181,"Revenue",'Main Work'!J$2:J$181,A12) -> 0 | C12: =SUMIFS('Main Work'!F$2:F$181,'Main Work'!E$2:E$181,"Expense",'Main Work'!J$2:J$181,A12) -> 0 | D12: =B12-C12 -> 0
A13: Dec | B13: =SUMIFS('Main Work'!F$2:F$181,'Main Work'!E$2:E$181,"Revenue",'Main Work'!J$2:J$181,A13) -> 0 | C13: =SUMIFS('Main Work'!F$2:F$181,'Main Work'!E$2:E$181,"Expense",'Main Work'!J$2:J$181,A13) -> 0 | D13: =B13-C13 -> 0

Sheet Department Budget Analysis
A1: Department | B1: Actual | C1: Budget | D1: Variance | E1: Variance%
A2: {=_xlfn.UNIQUE('Main Work'!C2:C181)} -> Sales | B2: =SUMIFS('Main Work'!F$2:F$181,'Main Work'!C$2:C$181,A2,'Main Work'!E$2:E$181,"Expense") -> 134953 | C2: =SUMIFS('Main Work'!G$2:G$181,'Main Work'!C$2:C$181,A2,'Main Work'!E$2:E$181,"Expense") -> 138305 | D2: =B2-C2 -> -3352 | E2: =D2/C2 -> -0.024236289
A3: Administration | B3: =SUMIFS('Main Work'!F$2:F$181,'Main Work'!C$2:C$181,A3,'Main Work'!E$2:E$181,"Expense") -> 97042 | C3: =SUMIFS('Main Work'!G$2:G$181,'Main Work'!C$2:C$181,A3,'Main Work'!E$2:E$181,"Expense") -> 100097 | D3: =B3-C3 -> -3055 | E3: =D3/C3 -> -0.030520395
A4: Operations | B4: =SUMIFS('Main Work'!F$2:F$181,'Main Work'!C$2:C$181,A4,'Main Work'!E$2:E$181,"Expense") -> 98095 | C4: =SUMIFS('Main Work'!G$2:G$181,'Main Work'!C$2:C$181,A4,'Main Work'!E$2:E$181,"Expense") -> 102026 | D4: =B4-C4 -> -3931 | E4: =D4/C4 -> -0.038529394
A5: Finance | B5: =SUMIFS('Main Work'!F$2:F$181,'Main Work'!C$2:C$181,A5,'Main Work'!E$2:E$181,"Expense") -> 126197 | C5: =SUMIFS('Main Work'!G$2:G$181,'Main Work'!C$2:C$181,A5,'Main Work'!E$2:E$181,"Expense") -> 131865 | D5: =B5-C5 -> -5668 | E5: =D5/C5 -> -0.042983354

Sheet Category Budget Analysis
A1: Category | B1: Actual | C1: Budget | D1: Variance | E1: Variance%
A2: {=_xlfn.UNIQUE('Main Work'!D2:D181)} -> Office Supplies | B2: =SUMIFS('Main Work'!F$2:F$181,'Main Work'!D$2:D$181,A2,'Main Work'!E$2:E$181,"Expense") -> 105273 | C2: =SUMIFS('Main Work'!G$2:G$181,'Main Work'!D$2:D$181,A2,'Main Work'!E$2:E$181,"Expense") -> 107266 | D2: =B2-C2 -> -1993 | E2: =IFERROR(D2/C2,0) -> -0.018579979
A3: Sales | B3: =SUMIFS('Main Work'!F$2:F$181,'Main Work'!D$2:D$181,A3,'Main Work'!E$2:E$181,"Expense") -> 0 | C3: =SUMIFS('Main Work'!G$2:G$181,'Main Work'!D$2:D$181,A3,'Main Work'!E$2:E$181,"Expense") -> 0 | D3: =B3-C3 -> 0 | E3: =IFERROR(D3/C3,0) -> 0
A4: Utilities | B4: =SUMIFS('Main Work'!F$2:F$181,'Main Work'!D$2:D$181,A4,'Main Work'!E$2:E$181,"Expense") -> 48873 | C4: =SUMIFS('Main Work'!G$2:G$181,'Main Work'!D$2:D$181,A4,'Main Work'!E$2:E$181,"Expense") -> 52456 | D4: =B4-C4 -> -3583 | E4: =IFERROR(D4/C4,0) -> -0.068304865
A5: Rent | B5: =SUMIFS('Main Work'!F$2:F$181,'Main Work'!D$2:D$181,A5,'Main Work'!E$2:E$181,"Expense") -> 65473 | C5: =SUMIFS('Main Work'!G$2:G$181,'Main Work'!D$2:D$181,A5,'Main Work'!E$2:E$181,"Expense") -> 68748 | D5: =B5-C5 -> -3275 | E5: =IFERROR(D5/C5,0) -> -0.047637749
A6: Marketing | B6: =SUMIFS('Main Work'!F$2:F$181,'Main Work'!D$2:D$181,A6,'Main Work'!E$2:E$181,"Expense") -> 82806 | C6: =SUMIFS('Main Work'!G$2:G$181,'Main Work'!D$2:D$181,A6,'Main Work'!E$2:E$181,"Expense") -> 83090 | D6: =B6-C6 -> -284 | E6: =IFERROR(D6/C6,0) -> -0.0034179805
A7: Consulting | B7: =SUMIFS('Main Work'!F$2:F$181,'Main Work'!D$2:D$181,A7,'Main Work'!E$2:E$181,"Expense") -> 0 | C7: =SUMIFS('Main Work'!G$2:G$181,'Main Work'!D$2:D$181,A7,'Main Work'!E$2:E$181,"Expense") -> 0 | D7: =B7-C7 -> 0 | E7: =IFERROR(D7/C7,0) -> 0
A8: Transport | B8: =SUMIFS('Main Work'!F$2:F$181,'Main Work'!D$2:D$181,A8,'Main Work'!E$2:E$181,"Expense") -> 59773 | C8: =SUMIFS('Main Work'!G$2:G$181,'Main Work'!D$2:D$181,A8,'Main Work'!E$2:E$181,"Expense") -> 60968 | D8: =B8-C8 -> -1195 | E8: =IFERROR(D8/C8,0) -> -0.019600446
A9: Software | B9: =SUMIFS('Main Work'!F$2:F$181,'Main Work'!D$2:D$181,A9,'Main Work'!E$2:E$181,"Expense") -> 94089 | C9: =SUMIFS('Main Work'!G$2:G$181,'Main Work'!D$2:D$181,A9,'Main Work'!E$2:E$181,"Expense") -> 99765 | D9: =B9-C9 -> -5676 | E9: =IFERROR(D9/C9,0) -> -0.0568937

Sheet Top Expense Categories
A1: Type | B1: Expense
A3: Category | B3: Sum of Actual_Amount_GHS
A4: Office Supplies | B4: 105273
A5: Software | B5: 94089
A6: Marketing | B6: 82806
A7: Rent | B7: 65473
A8: Transport | B8: 59773
A9: Utilities | B9: 48873
A10: Grand Total | B10: 456287

Sheet Expenses by Department
A1: Type | B1: Expense
A3: Department | B3: Sum of Actual_Amount_GHS
A4: Sales | B4: 134953
A5: Finance | B5: 126197
A6: Operations | B6: 98095
A7: Administration | B7: 97042
A8: Grand Total | B8: 456287

Sheet Management Insight
A1: Management Insight
B3: Management Insight
A4: No.1 | B4: Total revenue was GHS 318,721, while total expenses were GHS 456,287, resulting in a loss of GHS 137,566. This indicates that expenses exceeded the revenue generated during the period and should be reviewed for opportunities to improve profitability.
A5: No.2 | B5: Office Supplies was the highest expense category at GHS 105,273, followed by Software at GHS 94,089 and Marketing at GHS 82,806. These three categories accounted for a significant portion of total expenses and should be key areas for cost monitoring.
A6: No.3 | B6: Sales recorded the highest departmental expense at GHS 134,953, followed by Finance at GHS 126,197. Operations and Administration recorded GHS 98,095 and GHS 97,042 respectively, indicating that Sales and Finance were the two largest departmental cost centres during the period.
A7: No.4 | B7: All four departments recorded actual expenses below budget. Finance had the largest underspend at GHS 5,668 (4.30% below budget), followed by Operations at GHS 3,931 (3.85%), Sales at GHS 3,352 (2.42%), and Administration at GHS 3,055 (3.05%). This indicates that departmental spending remained within budget across the period.
A8: No.5 | B8: Utilities and Software recorded the largest percentage underspends among the expense categories, at 6.83% and 5.69% below budget respectively. Utilities was GHS 3,583 below budget, while Software was GHS 5,676 below budget, highlighting the largest category-level deviations from planned spending.
A9: No.6 | B9: Marketing recorded actual expenses of GHS 82,806 against a budget of GHS 83,090, resulting in an underspend of only GHS 284 (0.34%). This was the closest actual-to-budget performance among the active expense categories, indicating that Marketing spending was closely aligned with the planned amount.

Sheet Dashboard
A1: DAY 2 FINANCIAL ANALYSIS DASHBOARD
A3: Total Revenue | B3: 318721 | C3: Total Expenses | D3: 456287 | E3: Profit/(Loss) | F3: -137566 | G3: Profit Margin | H3: -0.4316
